rng/__init__.py
rng_wijesooriya-0.0.3.dist-info/LICENSE
rng_wijesooriya-0.0.3.dist-info/METADATA
rng_wijesooriya-0.0.3.dist-info/WHEEL
rng_wijesooriya-0.0.3.dist-info/top_level.txt
rng_wijesooriya-0.0.3.dist-info/RECORD
