Metadata-Version: 2.1
Name: rng-wijesooriya
Version: 0.0.3
Summary: Random Number Game
Home-page: UNKNOWN
Author: Kiran Wijesooriya
Author-email: kiranw1000@gmail.com
License: UNKNOWN
Platform: UNKNOWN
Classifier: Programming Language :: Python :: 3
Classifier: License :: OSI Approved :: MIT License
Classifier: Operating System :: OS Independent
Requires-Python: >=3.6
